setup.cfg
setup.py
./scripts/ecope
application/__init__.py
application/api.py
application/cli.py
application/scrap.py
application/utils.py
ecope.egg-info/PKG-INFO
ecope.egg-info/SOURCES.txt
ecope.egg-info/dependency_links.txt
ecope.egg-info/requires.txt
ecope.egg-info/top_level.txt