Metadata-Version: 2.1
Name: ecope
Version: 0.1.3
Summary: Ecommerce Perú Scrap CLI is a project open source that extract products data by category and export to csv, json and other structure format files
Home-page: https://github.com/djego/ecommerce-peru-scrap-cli
Author: Diego Machaca
Author-email: diegomachaca@gmail.com
License: UNKNOWN
Keywords: scraping,peru,ecommerce,csv,json
Platform: UNKNOWN
Requires-Python: >=3.7
